config/ollama_stable_code.yml
tldrai/__init__.py
tldrai/cli.py
tldrai/modules/__init__.py
tldrai/modules/generation_pipeline/__init__.py
tldrai/modules/generation_pipeline/ollama_pipeline.py
tldrai/modules/pre_inference/pre_summarization.py
tldrai/modules/similarity_scoring/__init__.py
tldrai/modules/similarity_scoring/sentence_similarity.py
tldrai/modules/stack_overflow/fetch.py
tldrai/modules/stack_overflow/pipeline.py
tldrai/modules/stack_overflow/process.py
tldrai/modules/stack_overflow/search.py
tldrai/modules/utils/__init__.py
tldrai/modules/utils/exceptions.py
tldrai/modules/utils/gpu.py
tldrai/modules/utils/logging.py
tldrai/run.py
tldrai-0.2.5.dist-info/LICENSE
tldrai-0.2.5.dist-info/METADATA
tldrai-0.2.5.dist-info/WHEEL
tldrai-0.2.5.dist-info/entry_points.txt
tldrai-0.2.5.dist-info/RECORD
