Metadata-Version: 2.1
Name: tldrai
Version: 0.2.5
Summary: CLI tool to give quick step-by-step answers to tech questions. Powered by the LLMs and StackOverflow.
Author: omalinovskyi
Author-email: orest0206@gmail.com
Requires-Python: >=3.11,<4.0
Classifier: Programming Language :: Python :: 3
Classifier: Programming Language :: Python :: 3.11
Classifier: Programming Language :: Python :: 3.12
Requires-Dist: beautifulsoup4 (>=4.12.3,<5.0.0)
Requires-Dist: click (>=8.1.7,<9.0.0)
Requires-Dist: hydra-core (>=1.3.2,<2.0.0)
Requires-Dist: lxml (>=5.2.2,<6.0.0)
Requires-Dist: ollama (>=0.2.1,<0.3.0)
Requires-Dist: pandas (>=2.2.2,<3.0.0)
Requires-Dist: sentence-transformers (>=2.5.1,<3.0.0)
Requires-Dist: stackapi (>=0.3.0,<0.4.0)
